setup.py
distributions_tut/Binomialdistribution.py
distributions_tut/Gaussiandistribution.py
distributions_tut/Generaldistribution.py
distributions_tut/__init__.py
distributions_tut.egg-info/PKG-INFO
distributions_tut.egg-info/SOURCES.txt
distributions_tut.egg-info/dependency_links.txt
distributions_tut.egg-info/not-zip-safe
distributions_tut.egg-info/top_level.txt