Metadata-Version: 1.0
Name: distributions-tut
Version: 0.1
Summary: Gaussian distributions
Home-page: UNKNOWN
Author: Andrii Iudin
Author-email: UNKNOWN
License: UNKNOWN
Platform: UNKNOWN
